README.md
setup.cfg
setup.py
ehr_functions/__init__.py
ehr_functions.egg-info/PKG-INFO
ehr_functions.egg-info/SOURCES.txt
ehr_functions.egg-info/dependency_links.txt
ehr_functions.egg-info/requires.txt
ehr_functions.egg-info/top_level.txt
ehr_functions/features/__init__.py
ehr_functions/features/build_features.py
ehr_functions/features/clinics.py
ehr_functions/features/clustering.py
ehr_functions/features/code_descriptions.py
ehr_functions/features/code_groups.py
ehr_functions/features/codes.py
ehr_functions/features/convert_codes.py
ehr_functions/features/demographics.py
ehr_functions/features/embeddings.py
ehr_functions/features/equation.py
ehr_functions/features/feature_selection.py
ehr_functions/features/filter_dataset.py
ehr_functions/features/meds.py
ehr_functions/features/occurrence.py
ehr_functions/features/symptoms.py
ehr_functions/features/windows.py
ehr_functions/files/__init__.py
ehr_functions/models/__init__.py
ehr_functions/models/autoencoder.py
ehr_functions/models/nn.py
ehr_functions/models/predict_model.py
ehr_functions/models/rnn.py
ehr_functions/models/save_model.py
ehr_functions/models/train_model.py
ehr_functions/models/metrics/__init__.py
ehr_functions/models/metrics/_base.py
ehr_functions/models/metrics/binary_classification.py
ehr_functions/models/metrics/roc_curve.py
ehr_functions/models/retain_experiment/__init__.py
ehr_functions/models/retain_experiment/count_diagnoses.py
ehr_functions/models/retain_experiment/process_mimic.py
ehr_functions/models/retain_experiment/process_nicoe.py
ehr_functions/models/retain_experiment/train.py
ehr_functions/models/retain_experiment/retain/__init__.py
ehr_functions/models/retain_experiment/retain/callbacks.py
ehr_functions/models/retain_experiment/retain/freeze_padding.py
ehr_functions/models/retain_experiment/retain/model.py
ehr_functions/models/retain_experiment/retain/sequence_builder.py
ehr_functions/models/types/__init__.py
ehr_functions/models/types/_base.py
ehr_functions/models/types/_gridsearch.py
ehr_functions/models/types/_sklearn.py
ehr_functions/models/types/adaboost.py
ehr_functions/models/types/elastic_net.py
ehr_functions/models/types/linear_regression.py
