Metadata-Version: 2.1
Name: ehr-functions
Version: 0.2.3
Summary: A library for EHR related functions.
Home-page: https://github.com/fdabek1/ehr-functions
Author: Filip Dabek
License: MIT
Download-URL: https://github.com/fdabek1/ehr-functions/archive/v0.1.0.tar.gz
Keywords: ehr,functions,library
Platform: UNKNOWN
Classifier: Development Status :: 3 - Alpha
Classifier: Intended Audience :: Developers
Classifier: Topic :: Software Development :: Build Tools
Classifier: License :: OSI Approved :: MIT License
Classifier: Programming Language :: Python :: 3
Classifier: Programming Language :: Python :: 3.8
